{
  "lastUpdated": "2026-04-02T07:29:16.363544",
  "events": [
    {
      "title": "Midwest Defense Innovation Summit",
      "description": "Midwest Defense Innovation Summit",
      "url": "https://techpoint.org/tech-events/",
      "date": "2026-04-08T00:00:00",
      "source": "TechPoint Indiana Events",
      "location": {
        "name": "Indianapolis",
        "address": "Indianapolis, IN",
        "lat": 39.7684,
        "lng": -86.1581
      },
      "features": {
        "free": false,
        "food": false,
        "appetizers": false,
        "nonAlcoholDrinks": false,
        "alcoholDrinks": false,
        "captainForged": false
      },
      "organizer": "TechPoint Indiana Events",
      "id": "6091790715172834677"
    },
    {
      "title": "Momentum: Fueling Entrepreneurs, Fast-Tracking Ideas",
      "description": "Momentum: Fueling Entrepreneurs, Fast-Tracking Ideas",
      "url": "https://techpoint.org/tech-events/",
      "date": "2026-04-08T00:00:00",
      "source": "TechPoint Indiana Events",
      "location": {
        "name": "Indianapolis",
        "address": "Indianapolis, IN",
        "lat": 39.7684,
        "lng": -86.1581
      },
      "features": {
        "free": false,
        "food": false,
        "appetizers": false,
        "nonAlcoholDrinks": false,
        "alcoholDrinks": false,
        "captainForged": false
      },
      "organizer": "TechPoint Indiana Events",
      "id": "1967724516338353392"
    },
    {
      "title": "University of Indianapolis AI Summit",
      "description": "University of Indianapolis AI Summit",
      "url": "https://techpoint.org/tech-events/",
      "date": "2026-04-09T00:00:00",
      "source": "TechPoint Indiana Events",
      "location": {
        "name": "Indianapolis",
        "address": "Indianapolis, Indiana",
        "lat": 39.7684,
        "lng": -86.1581
      },
      "features": {
        "free": false,
        "food": false,
        "appetizers": false,
        "nonAlcoholDrinks": false,
        "alcoholDrinks": false,
        "captainForged": false
      },
      "organizer": "TechPoint Indiana Events",
      "id": "5075669731780122984"
    },
    {
      "title": "ClickSide Chat: Women Who Lead & The Power to Persist",
      "description": "ClickSide Chat: Women Who Lead & The Power to Persist",
      "url": "https://techpoint.org/tech-events/",
      "date": "2026-04-15T00:00:00",
      "source": "TechPoint Indiana Events",
      "location": {
        "name": "Indianapolis",
        "address": "Indianapolis, IN",
        "lat": 39.7684,
        "lng": -86.1581
      },
      "features": {
        "free": false,
        "food": false,
        "appetizers": false,
        "nonAlcoholDrinks": false,
        "alcoholDrinks": false,
        "captainForged": false
      },
      "organizer": "TechPoint Indiana Events",
      "id": "5104083649039697494"
    },
    {
      "title": "From Fragmented Systems to Agentic Enterprise: How Engineering & Construction Leaders Are Using Workato + AI To Redesign Project Delivery",
      "description": "From Fragmented Systems to Agentic Enterprise: How Engineering & Construction Leaders Are Using Workato + AI To Redesign Project Delivery",
      "url": "https://techpoint.org/tech-events/",
      "date": "2026-04-22T00:00:00",
      "source": "TechPoint Indiana Events",
      "location": {
        "name": "Indianapolis",
        "address": "Indianapolis, IN",
        "lat": 39.7684,
        "lng": -86.1581
      },
      "features": {
        "free": false,
        "food": false,
        "appetizers": false,
        "nonAlcoholDrinks": false,
        "alcoholDrinks": false,
        "captainForged": false
      },
      "organizer": "TechPoint Indiana Events",
      "id": "7625011680161103352"
    },
    {
      "title": "IBJ Power Breakfast: Life Sciences",
      "description": "IBJ Power Breakfast: Life Sciences",
      "url": "https://techpoint.org/tech-events/",
      "date": "2026-04-23T00:00:00",
      "source": "TechPoint Indiana Events",
      "location": {
        "name": "Indianapolis",
        "address": "Indianapolis, IN",
        "lat": 39.7684,
        "lng": -86.1581
      },
      "features": {
        "free": false,
        "food": true,
        "appetizers": false,
        "nonAlcoholDrinks": false,
        "alcoholDrinks": false,
        "captainForged": false
      },
      "organizer": "TechPoint Indiana Events",
      "id": "1266891253484443165"
    },
    {
      "title": "TechPoint Mira Awards",
      "description": "TechPoint Mira Awards",
      "url": "https://techpoint.org/tech-events/",
      "date": "2026-04-24T00:00:00",
      "source": "TechPoint Indiana Events",
      "location": {
        "name": "Indianapolis",
        "address": "Indianapolis, IN",
        "lat": 39.7684,
        "lng": -86.1581
      },
      "features": {
        "free": false,
        "food": false,
        "appetizers": false,
        "nonAlcoholDrinks": false,
        "alcoholDrinks": false,
        "captainForged": false
      },
      "organizer": "TechPoint Indiana Events",
      "id": "1086696419932528276"
    },
    {
      "title": "Data Day 2026: From Data to Impact: Building Indiana's Intelligent Future",
      "description": "Data Day 2026: From Data to Impact: Building Indiana's Intelligent Future",
      "url": "https://techpoint.org/tech-events/",
      "date": "2026-04-30T00:00:00",
      "source": "TechPoint Indiana Events",
      "location": {
        "name": "Indianapolis",
        "address": "Indianapolis, IN",
        "lat": 39.7684,
        "lng": -86.1581
      },
      "features": {
        "free": false,
        "food": false,
        "appetizers": false,
        "nonAlcoholDrinks": false,
        "alcoholDrinks": false,
        "captainForged": false
      },
      "organizer": "TechPoint Indiana Events",
      "id": "230402135586868145"
    },
    {
      "title": "Student Innovation & Excellence Showcase",
      "description": "Student Innovation & Excellence Showcase",
      "url": "https://techpoint.org/tech-events/",
      "date": "2026-04-30T00:00:00",
      "source": "TechPoint Indiana Events",
      "location": {
        "name": "Indianapolis",
        "address": "Indianapolis, IN",
        "lat": 39.7684,
        "lng": -86.1581
      },
      "features": {
        "free": false,
        "food": false,
        "appetizers": false,
        "nonAlcoholDrinks": false,
        "alcoholDrinks": false,
        "captainForged": false
      },
      "organizer": "TechPoint Indiana Events",
      "id": "1508951245902696790"
    },
    {
      "title": "AnalytiXIN Community of Practice: Infrastructure + Sustainability",
      "description": "AnalytiXIN Community of Practice: Infrastructure + Sustainability",
      "url": "https://techpoint.org/tech-events/",
      "date": "2026-04-30T00:00:00",
      "source": "TechPoint Indiana Events",
      "location": {
        "name": "Indianapolis",
        "address": "Indianapolis, IN",
        "lat": 39.7684,
        "lng": -86.1581
      },
      "features": {
        "free": false,
        "food": false,
        "appetizers": false,
        "nonAlcoholDrinks": false,
        "alcoholDrinks": false,
        "captainForged": false
      },
      "organizer": "TechPoint Indiana Events",
      "id": "3572304942104496478"
    },
    {
      "title": "gBETA Indiana Showcase",
      "description": "gBETA Indiana Showcase",
      "url": "https://techpoint.org/tech-events/",
      "date": "2026-04-30T00:00:00",
      "source": "TechPoint Indiana Events",
      "location": {
        "name": "Indianapolis",
        "address": "Indianapolis, IN",
        "lat": 39.7684,
        "lng": -86.1581
      },
      "features": {
        "free": false,
        "food": false,
        "appetizers": false,
        "nonAlcoholDrinks": false,
        "alcoholDrinks": false,
        "captainForged": false
      },
      "organizer": "TechPoint Indiana Events",
      "id": "4076658927561936936"
    },
    {
      "title": "CFA Indianapolis Annual Investment Forum presented by EQT",
      "description": "CFA Indianapolis Annual Investment Forum presented by EQT",
      "url": "https://techpoint.org/tech-events/",
      "date": "2026-05-12T00:00:00",
      "source": "TechPoint Indiana Events",
      "location": {
        "name": "Indianapolis",
        "address": "Indianapolis, Indiana",
        "lat": 39.7684,
        "lng": -86.1581
      },
      "features": {
        "free": false,
        "food": false,
        "appetizers": false,
        "nonAlcoholDrinks": false,
        "alcoholDrinks": false,
        "captainForged": false
      },
      "organizer": "TechPoint Indiana Events",
      "id": "6392814302916933165"
    },
    {
      "title": "Momentum: Fueling Entrepreneurs, Fast-Tracking Ideas",
      "description": "Momentum: Fueling Entrepreneurs, Fast-Tracking Ideas",
      "url": "https://techpoint.org/tech-events/",
      "date": "2026-05-13T00:00:00",
      "source": "TechPoint Indiana Events",
      "location": {
        "name": "Indianapolis",
        "address": "Indianapolis, IN",
        "lat": 39.7684,
        "lng": -86.1581
      },
      "features": {
        "free": false,
        "food": false,
        "appetizers": false,
        "nonAlcoholDrinks": false,
        "alcoholDrinks": false,
        "captainForged": false
      },
      "organizer": "TechPoint Indiana Events",
      "id": "5778291184324445859"
    },
    {
      "title": "2026 Spring Networking Event at the Indianapolis Motor Speedway",
      "description": "2026 Spring Networking Event at the Indianapolis Motor Speedway",
      "url": "https://techpoint.org/tech-events/",
      "date": "2026-05-13T00:00:00",
      "source": "TechPoint Indiana Events",
      "location": {
        "name": "Indianapolis",
        "address": "Indianapolis, Indiana",
        "lat": 39.7684,
        "lng": -86.1581
      },
      "features": {
        "free": false,
        "food": false,
        "appetizers": true,
        "nonAlcoholDrinks": false,
        "alcoholDrinks": false,
        "captainForged": false
      },
      "organizer": "TechPoint Indiana Events",
      "id": "7566552620064317004"
    },
    {
      "title": "1 Million Cups Indianapolis",
      "description": "Join entrepreneurs for coffee, conversation, and connections. Two startup presentations followed by community feedback and networking.",
      "url": "https://www.1millioncups.com/indy",
      "date": "2026-04-08T09:00:00",
      "source": "1 Million Cups Indianapolis",
      "location": {
        "name": "Indianapolis",
        "address": "Indianapolis, Indiana",
        "lat": 39.7684,
        "lng": -86.1581
      },
      "features": {
        "free": false,
        "food": false,
        "appetizers": true,
        "nonAlcoholDrinks": true,
        "alcoholDrinks": false,
        "captainForged": false
      },
      "organizer": "1 Million Cups Indianapolis",
      "id": "7268619525144403018"
    },
    {
      "title": "1 Million Cups Indianapolis",
      "description": "Join entrepreneurs for coffee, conversation, and connections. Two startup presentations followed by community feedback and networking.",
      "url": "https://www.1millioncups.com/indy",
      "date": "2026-05-06T09:00:00",
      "source": "1 Million Cups Indianapolis",
      "location": {
        "name": "Indianapolis",
        "address": "Indianapolis, Indiana",
        "lat": 39.7684,
        "lng": -86.1581
      },
      "features": {
        "free": false,
        "food": false,
        "appetizers": true,
        "nonAlcoholDrinks": true,
        "alcoholDrinks": false,
        "captainForged": false
      },
      "organizer": "1 Million Cups Indianapolis",
      "id": "2980397966873723324"
    },
    {
      "title": "1 Million Cups Indianapolis",
      "description": "Join entrepreneurs for coffee, conversation, and connections. Two startup presentations followed by community feedback and networking.",
      "url": "https://www.1millioncups.com/indy",
      "date": "2026-06-03T09:00:00",
      "source": "1 Million Cups Indianapolis",
      "location": {
        "name": "Indianapolis",
        "address": "Indianapolis, Indiana",
        "lat": 39.7684,
        "lng": -86.1581
      },
      "features": {
        "free": false,
        "food": false,
        "appetizers": true,
        "nonAlcoholDrinks": true,
        "alcoholDrinks": false,
        "captainForged": false
      },
      "organizer": "1 Million Cups Indianapolis",
      "id": "3521014965791521174"
    },
    {
      "title": "1 Million Cups Indianapolis",
      "description": "Join entrepreneurs for coffee, conversation, and connections. Two startup presentations followed by community feedback and networking.",
      "url": "https://www.1millioncups.com/indy",
      "date": "2026-07-08T09:00:00",
      "source": "1 Million Cups Indianapolis",
      "location": {
        "name": "Indianapolis",
        "address": "Indianapolis, Indiana",
        "lat": 39.7684,
        "lng": -86.1581
      },
      "features": {
        "free": false,
        "food": false,
        "appetizers": true,
        "nonAlcoholDrinks": true,
        "alcoholDrinks": false,
        "captainForged": false
      },
      "organizer": "1 Million Cups Indianapolis",
      "id": "7407967014299200584"
    },
    {
      "title": "1 Million Cups Indianapolis",
      "description": "Join entrepreneurs for coffee, conversation, and connections. Two startup presentations followed by community feedback and networking.",
      "url": "https://www.1millioncups.com/indy",
      "date": "2026-08-05T09:00:00",
      "source": "1 Million Cups Indianapolis",
      "location": {
        "name": "Indianapolis",
        "address": "Indianapolis, Indiana",
        "lat": 39.7684,
        "lng": -86.1581
      },
      "features": {
        "free": false,
        "food": false,
        "appetizers": true,
        "nonAlcoholDrinks": true,
        "alcoholDrinks": false,
        "captainForged": false
      },
      "organizer": "1 Million Cups Indianapolis",
      "id": "2235445531157277342"
    },
    {
      "title": "1 Million Cups Indianapolis",
      "description": "Join entrepreneurs for coffee, conversation, and connections. Two startup presentations followed by community feedback and networking.",
      "url": "https://www.1millioncups.com/indy",
      "date": "2026-09-02T09:00:00",
      "source": "1 Million Cups Indianapolis",
      "location": {
        "name": "Indianapolis",
        "address": "Indianapolis, Indiana",
        "lat": 39.7684,
        "lng": -86.1581
      },
      "features": {
        "free": false,
        "food": false,
        "appetizers": true,
        "nonAlcoholDrinks": true,
        "alcoholDrinks": false,
        "captainForged": false
      },
      "organizer": "1 Million Cups Indianapolis",
      "id": "859502671459346161"
    },
    {
      "title": "1 Million Cups Indianapolis",
      "description": "Join entrepreneurs for coffee, conversation, and connections. Two startup presentations followed by community feedback and networking.",
      "url": "https://www.1millioncups.com/indy",
      "date": "2026-10-07T09:00:00",
      "source": "1 Million Cups Indianapolis",
      "location": {
        "name": "Indianapolis",
        "address": "Indianapolis, Indiana",
        "lat": 39.7684,
        "lng": -86.1581
      },
      "features": {
        "free": false,
        "food": false,
        "appetizers": true,
        "nonAlcoholDrinks": true,
        "alcoholDrinks": false,
        "captainForged": false
      },
      "organizer": "1 Million Cups Indianapolis",
      "id": "883456360453872621"
    },
    {
      "title": "1 Million Cups Indianapolis",
      "description": "Join entrepreneurs for coffee, conversation, and connections. Two startup presentations followed by community feedback and networking.",
      "url": "https://www.1millioncups.com/indy",
      "date": "2026-11-04T09:00:00",
      "source": "1 Million Cups Indianapolis",
      "location": {
        "name": "Indianapolis",
        "address": "Indianapolis, Indiana",
        "lat": 39.7684,
        "lng": -86.1581
      },
      "features": {
        "free": false,
        "food": false,
        "appetizers": true,
        "nonAlcoholDrinks": true,
        "alcoholDrinks": false,
        "captainForged": false
      },
      "organizer": "1 Million Cups Indianapolis",
      "id": "7454043621890364917"
    },
    {
      "title": "1 Million Cups Indianapolis",
      "description": "Join entrepreneurs for coffee, conversation, and connections. Two startup presentations followed by community feedback and networking.",
      "url": "https://www.1millioncups.com/indy",
      "date": "2026-12-02T09:00:00",
      "source": "1 Million Cups Indianapolis",
      "location": {
        "name": "Indianapolis",
        "address": "Indianapolis, Indiana",
        "lat": 39.7684,
        "lng": -86.1581
      },
      "features": {
        "free": false,
        "food": false,
        "appetizers": true,
        "nonAlcoholDrinks": true,
        "alcoholDrinks": false,
        "captainForged": false
      },
      "organizer": "1 Million Cups Indianapolis",
      "id": "1736786180412830791"
    },
    {
      "title": "1 Million Cups Indianapolis",
      "description": "Join entrepreneurs for coffee, conversation, and connections. Two startup presentations followed by community feedback and networking.",
      "url": "https://www.1millioncups.com/indy",
      "date": "2027-01-06T09:00:00",
      "source": "1 Million Cups Indianapolis",
      "location": {
        "name": "Indianapolis",
        "address": "Indianapolis, Indiana",
        "lat": 39.7684,
        "lng": -86.1581
      },
      "features": {
        "free": false,
        "food": false,
        "appetizers": true,
        "nonAlcoholDrinks": true,
        "alcoholDrinks": false,
        "captainForged": false
      },
      "organizer": "1 Million Cups Indianapolis",
      "id": "1006066647232040768"
    },
    {
      "title": "1 Million Cups Indianapolis",
      "description": "Join entrepreneurs for coffee, conversation, and connections. Two startup presentations followed by community feedback and networking.",
      "url": "https://www.1millioncups.com/indy",
      "date": "2027-02-03T09:00:00",
      "source": "1 Million Cups Indianapolis",
      "location": {
        "name": "Indianapolis",
        "address": "Indianapolis, Indiana",
        "lat": 39.7684,
        "lng": -86.1581
      },
      "features": {
        "free": false,
        "food": false,
        "appetizers": true,
        "nonAlcoholDrinks": true,
        "alcoholDrinks": false,
        "captainForged": false
      },
      "organizer": "1 Million Cups Indianapolis",
      "id": "4472178470703528701"
    },
    {
      "title": "1 Million Cups Indianapolis",
      "description": "Join entrepreneurs for coffee, conversation, and connections. Two startup presentations followed by community feedback and networking.",
      "url": "https://www.1millioncups.com/indy",
      "date": "2027-03-03T09:00:00",
      "source": "1 Million Cups Indianapolis",
      "location": {
        "name": "Indianapolis",
        "address": "Indianapolis, Indiana",
        "lat": 39.7684,
        "lng": -86.1581
      },
      "features": {
        "free": false,
        "food": false,
        "appetizers": true,
        "nonAlcoholDrinks": true,
        "alcoholDrinks": false,
        "captainForged": false
      },
      "organizer": "1 Million Cups Indianapolis",
      "id": "8091349303283528499"
    },
    {
      "title": "1 Million Cups Indianapolis",
      "description": "Join entrepreneurs for coffee, conversation, and connections. Two startup presentations followed by community feedback and networking.",
      "url": "https://www.1millioncups.com/indy",
      "date": "2027-04-07T09:00:00",
      "source": "1 Million Cups Indianapolis",
      "location": {
        "name": "Indianapolis",
        "address": "Indianapolis, Indiana",
        "lat": 39.7684,
        "lng": -86.1581
      },
      "features": {
        "free": false,
        "food": false,
        "appetizers": true,
        "nonAlcoholDrinks": true,
        "alcoholDrinks": false,
        "captainForged": false
      },
      "organizer": "1 Million Cups Indianapolis",
      "id": "4295357148140569363"
    },
    {
      "title": "1 Million Cups Indianapolis",
      "description": "Join entrepreneurs for coffee, conversation, and connections. Two startup presentations followed by community feedback and networking.",
      "url": "https://www.1millioncups.com/indy",
      "date": "2027-05-05T09:00:00",
      "source": "1 Million Cups Indianapolis",
      "location": {
        "name": "Indianapolis",
        "address": "Indianapolis, Indiana",
        "lat": 39.7684,
        "lng": -86.1581
      },
      "features": {
        "free": false,
        "food": false,
        "appetizers": true,
        "nonAlcoholDrinks": true,
        "alcoholDrinks": false,
        "captainForged": false
      },
      "organizer": "1 Million Cups Indianapolis",
      "id": "6530196317828292142"
    },
    {
      "title": "1 Million Cups South Bend",
      "description": "Join entrepreneurs for coffee, conversation, and connections. Two startup presentations followed by community feedback and networking.",
      "url": "https://www.1millioncups.com/southbend",
      "date": "2026-04-08T08:00:00",
      "source": "1 Million Cups South Bend",
      "location": {
        "name": "South Bend",
        "address": "South Bend, Indiana",
        "lat": 41.6764,
        "lng": -86.252
      },
      "features": {
        "free": false,
        "food": false,
        "appetizers": true,
        "nonAlcoholDrinks": true,
        "alcoholDrinks": false,
        "captainForged": false
      },
      "organizer": "1 Million Cups South Bend",
      "id": "7672219137978030605"
    },
    {
      "title": "1 Million Cups South Bend",
      "description": "Join entrepreneurs for coffee, conversation, and connections. Two startup presentations followed by community feedback and networking.",
      "url": "https://www.1millioncups.com/southbend",
      "date": "2026-05-13T08:00:00",
      "source": "1 Million Cups South Bend",
      "location": {
        "name": "South Bend",
        "address": "South Bend, Indiana",
        "lat": 41.6764,
        "lng": -86.252
      },
      "features": {
        "free": false,
        "food": false,
        "appetizers": true,
        "nonAlcoholDrinks": true,
        "alcoholDrinks": false,
        "captainForged": false
      },
      "organizer": "1 Million Cups South Bend",
      "id": "6066357428170704247"
    },
    {
      "title": "1 Million Cups South Bend",
      "description": "Join entrepreneurs for coffee, conversation, and connections. Two startup presentations followed by community feedback and networking.",
      "url": "https://www.1millioncups.com/southbend",
      "date": "2026-06-10T08:00:00",
      "source": "1 Million Cups South Bend",
      "location": {
        "name": "South Bend",
        "address": "South Bend, Indiana",
        "lat": 41.6764,
        "lng": -86.252
      },
      "features": {
        "free": false,
        "food": false,
        "appetizers": true,
        "nonAlcoholDrinks": true,
        "alcoholDrinks": false,
        "captainForged": false
      },
      "organizer": "1 Million Cups South Bend",
      "id": "8007182389458718990"
    },
    {
      "title": "1 Million Cups South Bend",
      "description": "Join entrepreneurs for coffee, conversation, and connections. Two startup presentations followed by community feedback and networking.",
      "url": "https://www.1millioncups.com/southbend",
      "date": "2026-07-08T08:00:00",
      "source": "1 Million Cups South Bend",
      "location": {
        "name": "South Bend",
        "address": "South Bend, Indiana",
        "lat": 41.6764,
        "lng": -86.252
      },
      "features": {
        "free": false,
        "food": false,
        "appetizers": true,
        "nonAlcoholDrinks": true,
        "alcoholDrinks": false,
        "captainForged": false
      },
      "organizer": "1 Million Cups South Bend",
      "id": "8060249774617790186"
    },
    {
      "title": "1 Million Cups South Bend",
      "description": "Join entrepreneurs for coffee, conversation, and connections. Two startup presentations followed by community feedback and networking.",
      "url": "https://www.1millioncups.com/southbend",
      "date": "2026-08-12T08:00:00",
      "source": "1 Million Cups South Bend",
      "location": {
        "name": "South Bend",
        "address": "South Bend, Indiana",
        "lat": 41.6764,
        "lng": -86.252
      },
      "features": {
        "free": false,
        "food": false,
        "appetizers": true,
        "nonAlcoholDrinks": true,
        "alcoholDrinks": false,
        "captainForged": false
      },
      "organizer": "1 Million Cups South Bend",
      "id": "4302744588982307895"
    },
    {
      "title": "1 Million Cups South Bend",
      "description": "Join entrepreneurs for coffee, conversation, and connections. Two startup presentations followed by community feedback and networking.",
      "url": "https://www.1millioncups.com/southbend",
      "date": "2026-09-09T08:00:00",
      "source": "1 Million Cups South Bend",
      "location": {
        "name": "South Bend",
        "address": "South Bend, Indiana",
        "lat": 41.6764,
        "lng": -86.252
      },
      "features": {
        "free": false,
        "food": false,
        "appetizers": true,
        "nonAlcoholDrinks": true,
        "alcoholDrinks": false,
        "captainForged": false
      },
      "organizer": "1 Million Cups South Bend",
      "id": "1364710242457875063"
    },
    {
      "title": "1 Million Cups South Bend",
      "description": "Join entrepreneurs for coffee, conversation, and connections. Two startup presentations followed by community feedback and networking.",
      "url": "https://www.1millioncups.com/southbend",
      "date": "2026-10-14T08:00:00",
      "source": "1 Million Cups South Bend",
      "location": {
        "name": "South Bend",
        "address": "South Bend, Indiana",
        "lat": 41.6764,
        "lng": -86.252
      },
      "features": {
        "free": false,
        "food": false,
        "appetizers": true,
        "nonAlcoholDrinks": true,
        "alcoholDrinks": false,
        "captainForged": false
      },
      "organizer": "1 Million Cups South Bend",
      "id": "1383922179198028718"
    },
    {
      "title": "1 Million Cups South Bend",
      "description": "Join entrepreneurs for coffee, conversation, and connections. Two startup presentations followed by community feedback and networking.",
      "url": "https://www.1millioncups.com/southbend",
      "date": "2026-11-11T08:00:00",
      "source": "1 Million Cups South Bend",
      "location": {
        "name": "South Bend",
        "address": "South Bend, Indiana",
        "lat": 41.6764,
        "lng": -86.252
      },
      "features": {
        "free": false,
        "food": false,
        "appetizers": true,
        "nonAlcoholDrinks": true,
        "alcoholDrinks": false,
        "captainForged": false
      },
      "organizer": "1 Million Cups South Bend",
      "id": "2851778898327081917"
    },
    {
      "title": "1 Million Cups South Bend",
      "description": "Join entrepreneurs for coffee, conversation, and connections. Two startup presentations followed by community feedback and networking.",
      "url": "https://www.1millioncups.com/southbend",
      "date": "2026-12-09T08:00:00",
      "source": "1 Million Cups South Bend",
      "location": {
        "name": "South Bend",
        "address": "South Bend, Indiana",
        "lat": 41.6764,
        "lng": -86.252
      },
      "features": {
        "free": false,
        "food": false,
        "appetizers": true,
        "nonAlcoholDrinks": true,
        "alcoholDrinks": false,
        "captainForged": false
      },
      "organizer": "1 Million Cups South Bend",
      "id": "4134557298224894918"
    },
    {
      "title": "1 Million Cups South Bend",
      "description": "Join entrepreneurs for coffee, conversation, and connections. Two startup presentations followed by community feedback and networking.",
      "url": "https://www.1millioncups.com/southbend",
      "date": "2027-01-13T08:00:00",
      "source": "1 Million Cups South Bend",
      "location": {
        "name": "South Bend",
        "address": "South Bend, Indiana",
        "lat": 41.6764,
        "lng": -86.252
      },
      "features": {
        "free": false,
        "food": false,
        "appetizers": true,
        "nonAlcoholDrinks": true,
        "alcoholDrinks": false,
        "captainForged": false
      },
      "organizer": "1 Million Cups South Bend",
      "id": "1337853714314980417"
    },
    {
      "title": "1 Million Cups South Bend",
      "description": "Join entrepreneurs for coffee, conversation, and connections. Two startup presentations followed by community feedback and networking.",
      "url": "https://www.1millioncups.com/southbend",
      "date": "2027-02-10T08:00:00",
      "source": "1 Million Cups South Bend",
      "location": {
        "name": "South Bend",
        "address": "South Bend, Indiana",
        "lat": 41.6764,
        "lng": -86.252
      },
      "features": {
        "free": false,
        "food": false,
        "appetizers": true,
        "nonAlcoholDrinks": true,
        "alcoholDrinks": false,
        "captainForged": false
      },
      "organizer": "1 Million Cups South Bend",
      "id": "5594494580579617741"
    },
    {
      "title": "1 Million Cups South Bend",
      "description": "Join entrepreneurs for coffee, conversation, and connections. Two startup presentations followed by community feedback and networking.",
      "url": "https://www.1millioncups.com/southbend",
      "date": "2027-03-10T08:00:00",
      "source": "1 Million Cups South Bend",
      "location": {
        "name": "South Bend",
        "address": "South Bend, Indiana",
        "lat": 41.6764,
        "lng": -86.252
      },
      "features": {
        "free": false,
        "food": false,
        "appetizers": true,
        "nonAlcoholDrinks": true,
        "alcoholDrinks": false,
        "captainForged": false
      },
      "organizer": "1 Million Cups South Bend",
      "id": "2154908034564572547"
    },
    {
      "title": "1 Million Cups South Bend",
      "description": "Join entrepreneurs for coffee, conversation, and connections. Two startup presentations followed by community feedback and networking.",
      "url": "https://www.1millioncups.com/southbend",
      "date": "2027-04-14T08:00:00",
      "source": "1 Million Cups South Bend",
      "location": {
        "name": "South Bend",
        "address": "South Bend, Indiana",
        "lat": 41.6764,
        "lng": -86.252
      },
      "features": {
        "free": false,
        "food": false,
        "appetizers": true,
        "nonAlcoholDrinks": true,
        "alcoholDrinks": false,
        "captainForged": false
      },
      "organizer": "1 Million Cups South Bend",
      "id": "373730382278942034"
    },
    {
      "title": "1 Million Cups South Bend",
      "description": "Join entrepreneurs for coffee, conversation, and connections. Two startup presentations followed by community feedback and networking.",
      "url": "https://www.1millioncups.com/southbend",
      "date": "2027-05-12T08:00:00",
      "source": "1 Million Cups South Bend",
      "location": {
        "name": "South Bend",
        "address": "South Bend, Indiana",
        "lat": 41.6764,
        "lng": -86.252
      },
      "features": {
        "free": false,
        "food": false,
        "appetizers": true,
        "nonAlcoholDrinks": true,
        "alcoholDrinks": false,
        "captainForged": false
      },
      "organizer": "1 Million Cups South Bend",
      "id": "705348907687913179"
    },
    {
      "title": "March Madness Watch Party",
      "description": "Get ready for the best time of the year at The AMP! \ud83c\udfc0 \nJoin us March 17 through April 6 as we stream all the tournament action on the big screens. Grab your crew, order from your favorite AMP vendors, and catch every buzzer-beater, upset, and bracket-buster with us. \nWe\u2019ll have food and drink specials, games, and entertainment throughout the tournament \u2014 plus live DJ sets on March 20, March 27, April 3, and April 6 to keep the energy high between matchups. \nBasketball. Food. Fun.",
      "url": "https://16tech.com/event/march-madness-watch-party-2/",
      "date": "2026-04-04T00:00:00",
      "source": "16 Tech Innovation District",
      "location": {
        "name": "Indianapolis",
        "address": "Indianapolis, IN",
        "lat": 39.7684,
        "lng": -86.1581
      },
      "features": {
        "free": false,
        "food": false,
        "appetizers": false,
        "nonAlcoholDrinks": false,
        "alcoholDrinks": true,
        "captainForged": false
      },
      "organizer": "16 Tech Innovation District",
      "id": "7424229723546750227"
    },
    {
      "title": "Indy Winter Farmers Market",
      "description": "Come out to the Indy Winter Farmers Market every Saturday from 9am \u2013 12:30pm, until April 25th. With over 50 vendors, there is a little something for everyone!",
      "url": "https://16tech.com/event/indy-winter-farmers-market-92/",
      "date": "2026-04-04T09:00:00",
      "source": "16 Tech Innovation District",
      "location": {
        "name": "Indianapolis",
        "address": "Indianapolis, IN",
        "lat": 39.7684,
        "lng": -86.1581
      },
      "features": {
        "free": false,
        "food": false,
        "appetizers": false,
        "nonAlcoholDrinks": false,
        "alcoholDrinks": false,
        "captainForged": false
      },
      "organizer": "16 Tech Innovation District",
      "id": "7111456660284404766"
    },
    {
      "title": "March Madness Watch Party",
      "description": "Get ready for the best time of the year at The AMP! \ud83c\udfc0 \nJoin us March 17 through April 6 as we stream all the tournament action on the big screens. Grab your crew, order from your favorite AMP vendors, and catch every buzzer-beater, upset, and bracket-buster with us. \nWe\u2019ll have food and drink specials, games, and entertainment throughout the tournament \u2014 plus live DJ sets on March 20, March 27, April 3, and April 6 to keep the energy high between matchups. \nBasketball. Food. Fun.",
      "url": "https://16tech.com/event/march-madness-watch-party/",
      "date": "2026-04-06T00:00:00",
      "source": "16 Tech Innovation District",
      "location": {
        "name": "Indianapolis",
        "address": "Indianapolis, IN",
        "lat": 39.7684,
        "lng": -86.1581
      },
      "features": {
        "free": false,
        "food": false,
        "appetizers": false,
        "nonAlcoholDrinks": false,
        "alcoholDrinks": true,
        "captainForged": false
      },
      "organizer": "16 Tech Innovation District",
      "id": "7361090045534706372"
    },
    {
      "title": "Indy Winter Farmers Market",
      "description": "Come out to the Indy Winter Farmers Market every Saturday from 9am \u2013 12:30pm, until April 25th. With over 50 vendors, there is a little something for everyone!",
      "url": "https://16tech.com/event/indy-winter-farmers-market-93/",
      "date": "2026-04-11T09:00:00",
      "source": "16 Tech Innovation District",
      "location": {
        "name": "Indianapolis",
        "address": "Indianapolis, IN",
        "lat": 39.7684,
        "lng": -86.1581
      },
      "features": {
        "free": false,
        "food": false,
        "appetizers": false,
        "nonAlcoholDrinks": false,
        "alcoholDrinks": false,
        "captainForged": false
      },
      "organizer": "16 Tech Innovation District",
      "id": "5661749079031653923"
    },
    {
      "title": "Indy Winter Farmers Market",
      "description": "Come out to the Indy Winter Farmers Market every Saturday from 9am \u2013 12:30pm, until April 25th. With over 50 vendors, there is a little something for everyone!",
      "url": "https://16tech.com/event/indy-winter-farmers-market-94/",
      "date": "2026-04-18T09:00:00",
      "source": "16 Tech Innovation District",
      "location": {
        "name": "Indianapolis",
        "address": "Indianapolis, IN",
        "lat": 39.7684,
        "lng": -86.1581
      },
      "features": {
        "free": false,
        "food": false,
        "appetizers": false,
        "nonAlcoholDrinks": false,
        "alcoholDrinks": false,
        "captainForged": false
      },
      "organizer": "16 Tech Innovation District",
      "id": "1365702657110674316"
    },
    {
      "title": "IUI DISEnsemble Performance",
      "description": "IU Indy\u2019s DISEnsemble will present a performance of experimental and AI-integrated music, featuring original works that explore human\u2013machine collaboration, custom instruments, and improvisation.",
      "url": "https://16tech.com/event/iui-disensemble-performance/",
      "date": "2026-04-23T19:00:00",
      "source": "16 Tech Innovation District",
      "location": {
        "name": "Indianapolis",
        "address": "Indianapolis, IN",
        "lat": 39.7684,
        "lng": -86.1581
      },
      "features": {
        "free": false,
        "food": false,
        "appetizers": false,
        "nonAlcoholDrinks": false,
        "alcoholDrinks": false,
        "captainForged": false
      },
      "organizer": "16 Tech Innovation District",
      "id": "3412160653912649127"
    },
    {
      "title": "Indy Winter Farmers Market",
      "description": "Come out to the Indy Winter Farmers Market every Saturday from 9am \u2013 12:30pm, until April 25th. With over 50 vendors, there is a little something for everyone!",
      "url": "https://16tech.com/event/indy-winter-farmers-market-95/",
      "date": "2026-04-25T09:00:00",
      "source": "16 Tech Innovation District",
      "location": {
        "name": "Indianapolis",
        "address": "Indianapolis, IN",
        "lat": 39.7684,
        "lng": -86.1581
      },
      "features": {
        "free": false,
        "food": false,
        "appetizers": false,
        "nonAlcoholDrinks": false,
        "alcoholDrinks": false,
        "captainForged": false
      },
      "organizer": "16 Tech Innovation District",
      "id": "4032198644146189454"
    },
    {
      "title": "Pitch a Single Friend",
      "description": "16 of the most eligible singles will have their best friend pitching them to a crowd of 150+ mostly single people.",
      "url": "https://16tech.com/event/pitch-a-single-friend/",
      "date": "2026-05-15T18:00:00",
      "source": "16 Tech Innovation District",
      "location": {
        "name": "Indianapolis",
        "address": "Indianapolis, IN",
        "lat": 39.7684,
        "lng": -86.1581
      },
      "features": {
        "free": false,
        "food": false,
        "appetizers": false,
        "nonAlcoholDrinks": false,
        "alcoholDrinks": false,
        "captainForged": false
      },
      "organizer": "16 Tech Innovation District",
      "id": "7705934971563954473"
    },
    {
      "title": "Coffee & Conversation: April 2026",
      "description": "Mornings are better when we get together. \u2615\ufe0f \nImagine starting your day with a vibrant buzz, not just from your coffee, but from connecting with fellow local innovators. Our monthly Coffee & Conversation event is designed to do just that. \nJoin us on the second Thursday of every month at 8:30 AM for a morning of free coffee, delicious donuts and making valuable connections that can help propel your business forward. This event is specifically crafted to bring Fishers businesses and entrepreneurs",
      "url": "https://launchfishers.com/event-calendar/coffee-conversation-april-2026/",
      "date": "2026-04-09T08:30:00",
      "source": "Launch Fishers",
      "location": {
        "name": "Indianapolis",
        "address": "Indianapolis, IN",
        "lat": 39.7684,
        "lng": -86.1581
      },
      "features": {
        "free": true,
        "food": false,
        "appetizers": false,
        "nonAlcoholDrinks": true,
        "alcoholDrinks": false,
        "captainForged": false
      },
      "organizer": "Launch Fishers",
      "id": "2879566532087504020"
    },
    {
      "title": "Free Cowork Friday: April 2026",
      "description": "Each month on the final Friday, we open our doors to anyone interested in trying out coworking! Potential new members can come in and enjoy free coffee & coworking as they test drive what a Launch Fishers membership is all about. We provide a reliable place to work for all sorts of people: entrepreneurs, remote workers, consultants, and more! \nBenefits of Launch Fishers membership: a comfortable workspace, a great community of fellow coworkers, phone booths, meeting & conference rooms, in-house ",
      "url": "https://launchfishers.com/event-calendar/free-cowork-friday-april-2026/",
      "date": "2026-04-24T08:00:00",
      "source": "Launch Fishers",
      "location": {
        "name": "Indianapolis",
        "address": "Indianapolis, IN",
        "lat": 39.7684,
        "lng": -86.1581
      },
      "features": {
        "free": true,
        "food": false,
        "appetizers": false,
        "nonAlcoholDrinks": true,
        "alcoholDrinks": false,
        "captainForged": false
      },
      "organizer": "Launch Fishers",
      "id": "6147980054073883215"
    },
    {
      "title": "STARTUP MASTERY | Improving Healthcare Outcomes",
      "description": "How do we move the needle on patient health?\u00a0It starts with closing the gap between clinical care and daily life. \nJoin\u00a0Launch Fishers\u00a0and\u00a0Plug and Play Indiana\u00a0for the second installment of our 2026 Startup Mastery series. This quarter, we are diving deep into the technologies that keep patients on track in their care journeys. We\u2019re bringing together the founders, clinicians, and corporate leaders who are using collaborative platforms to slash readmission rates and revolutionize patient adhere",
      "url": "https://launchfishers.com/event-calendar/startup-mastery-improving-healthcare-outcomes/",
      "date": "2026-04-29T09:00:00",
      "source": "Launch Fishers",
      "location": {
        "name": "Indianapolis",
        "address": "Indianapolis, IN",
        "lat": 39.7684,
        "lng": -86.1581
      },
      "features": {
        "free": false,
        "food": false,
        "appetizers": false,
        "nonAlcoholDrinks": false,
        "alcoholDrinks": false,
        "captainForged": false
      },
      "organizer": "Launch Fishers",
      "id": "7023517875815039737"
    },
    {
      "title": "Coffee & Conversation: May 2026",
      "description": "Mornings are better when we get together. \u2615\ufe0f \nImagine starting your day with a vibrant buzz, not just from your coffee, but from connecting with fellow local innovators. Our monthly Coffee & Conversation event is designed to do just that. \nJoin us on the second Thursday of every month at 8:30 AM for a morning of free coffee, delicious donuts and making valuable connections that can help propel your business forward. This event is specifically crafted to bring Fishers businesses and entrepreneurs",
      "url": "https://launchfishers.com/event-calendar/coffee-conversation-may-2026/",
      "date": "2026-05-14T08:30:00",
      "source": "Launch Fishers",
      "location": {
        "name": "Indianapolis",
        "address": "Indianapolis, IN",
        "lat": 39.7684,
        "lng": -86.1581
      },
      "features": {
        "free": true,
        "food": false,
        "appetizers": false,
        "nonAlcoholDrinks": true,
        "alcoholDrinks": false,
        "captainForged": false
      },
      "organizer": "Launch Fishers",
      "id": "8684087310990188373"
    },
    {
      "title": "Free Cowork Friday: May 2026",
      "description": "Each month on the final Friday, we open our doors to anyone interested in trying out coworking! Potential new members can come in and enjoy free coffee & coworking as they test drive what a Launch Fishers membership is all about. We provide a reliable place to work for all sorts of people: entrepreneurs, remote workers, consultants, and more! \nBenefits of Launch Fishers membership: a comfortable workspace, a great community of fellow coworkers, phone booths, meeting & conference rooms, in-house ",
      "url": "https://launchfishers.com/event-calendar/free-cowork-friday-may-2026/",
      "date": "2026-05-29T08:00:00",
      "source": "Launch Fishers",
      "location": {
        "name": "Indianapolis",
        "address": "Indianapolis, IN",
        "lat": 39.7684,
        "lng": -86.1581
      },
      "features": {
        "free": true,
        "food": false,
        "appetizers": false,
        "nonAlcoholDrinks": true,
        "alcoholDrinks": false,
        "captainForged": false
      },
      "organizer": "Launch Fishers",
      "id": "4472564616268129725"
    },
    {
      "title": "Coffee & Conversation: June 2026",
      "description": "Mornings are better when we get together. \u2615\ufe0f \nImagine starting your day with a vibrant buzz, not just from your coffee, but from connecting with fellow local innovators. Our monthly Coffee & Conversation event is designed to do just that. \nJoin us on the second Thursday of every month at 8:30 AM for a morning of free coffee, delicious donuts and making valuable connections that can help propel your business forward. This event is specifically crafted to bring Fishers businesses and entrepreneurs",
      "url": "https://launchfishers.com/event-calendar/coffee-conversation-june-2026/",
      "date": "2026-06-11T08:30:00",
      "source": "Launch Fishers",
      "location": {
        "name": "Indianapolis",
        "address": "Indianapolis, IN",
        "lat": 39.7684,
        "lng": -86.1581
      },
      "features": {
        "free": true,
        "food": false,
        "appetizers": false,
        "nonAlcoholDrinks": true,
        "alcoholDrinks": false,
        "captainForged": false
      },
      "organizer": "Launch Fishers",
      "id": "9116354731857675252"
    },
    {
      "title": "Free Cowork Friday: June 2026",
      "description": "Each month on the final Friday, we open our doors to anyone interested in trying out coworking! Potential new members can come in and enjoy free coffee & coworking as they test drive what a Launch Fishers membership is all about. We provide a reliable place to work for all sorts of people: entrepreneurs, remote workers, consultants, and more! \nBenefits of Launch Fishers membership: a comfortable workspace, a great community of fellow coworkers, phone booths, meeting & conference rooms, in-house ",
      "url": "https://launchfishers.com/event-calendar/free-cowork-friday-june-2026/",
      "date": "2026-06-26T08:00:00",
      "source": "Launch Fishers",
      "location": {
        "name": "Indianapolis",
        "address": "Indianapolis, IN",
        "lat": 39.7684,
        "lng": -86.1581
      },
      "features": {
        "free": true,
        "food": false,
        "appetizers": false,
        "nonAlcoholDrinks": true,
        "alcoholDrinks": false,
        "captainForged": false
      },
      "organizer": "Launch Fishers",
      "id": "2330551260140339536"
    },
    {
      "title": "H7 Network, Noblesville, IN",
      "description": "H7 Indianapolis IN Business Networking\n**Perkins**\n*250 Noble Creek Dr., Noblesville, IN 46060, USA*\n\n[Add to Calendar](https://www.addevent.com/event/Em26135662)\n\n**H7 Noblesville** is our weekly networking meeting open to local B2B and B2C professionals. Experience the distinct, structural, difference from other networking groups, associations, and chambers. Our community of meetings are led by Champion Leadership.\n\n***All meetings welcome visitors, we'd love to show you what we're all about!*",
      "url": "https://www.meetup.com/h7-network-indianapolis/events/313801105/",
      "date": "2026-04-02T08:00:00",
      "source": "H7 Network Indianapolis Meetup",
      "location": {
        "name": "Noblesville",
        "address": "Noblesville, Indiana",
        "lat": 40.0456,
        "lng": -86.0086
      },
      "features": {
        "free": false,
        "food": false,
        "appetizers": true,
        "nonAlcoholDrinks": false,
        "alcoholDrinks": false,
        "captainForged": false
      },
      "organizer": "H7 Network Indianapolis Meetup",
      "id": "4015164784256847047"
    },
    {
      "title": "H7 Network, Carmel, IN",
      "description": "H7 Indianapolis IN Business Networking\n**Wolfies Grill - Carmel**\n*1162 Keystone Way S, Carmel, IN 46032, USA*\n\nH7 Carmel is our weekly networking meeting open to local B2B and B2C professionals. Experience the distinct, structural, difference from other networking groups, associations, and chambers. Our community of meetings are led by Champion Leadership.\n\n***All meetings welcome visitors, we'd love to show you what we're all about!***\n\n\\*\\*\\*Meeting Contact: \\*\\*\\*\n\n**Seth Wilson** *at* ***31",
      "url": "https://www.meetup.com/h7-network-indianapolis/events/313819780/",
      "date": "2026-04-06T12:00:00",
      "source": "H7 Network Indianapolis Meetup",
      "location": {
        "name": "Carmel",
        "address": "Carmel, Indiana",
        "lat": 39.9784,
        "lng": -86.118
      },
      "features": {
        "free": false,
        "food": false,
        "appetizers": true,
        "nonAlcoholDrinks": false,
        "alcoholDrinks": false,
        "captainForged": false
      },
      "organizer": "H7 Network Indianapolis Meetup",
      "id": "3741370996991285197"
    },
    {
      "title": "H7 Network, Westfield, IN",
      "description": "H7 Indianapolis IN Business Networking\n**Lincoln Square Pancake House**\n*3186 IN-32, Westfield, IN 46074, USA*\n\nH7 Westfield is our weekly networking meeting open to local B2B and B2C professionals. Experience the distinct, structural, difference from other networking groups, associations, and chambers. Our community of meetings are led by Champion Leadership.\n***All meetings welcome visitors, we'd love to show you what we're all about!***\n\n***Meeting Contact*:**\n\n**Andy Corman,** *andy@actrashh",
      "url": "https://www.meetup.com/h7-network-indianapolis/events/313833331/",
      "date": "2026-04-07T08:30:00",
      "source": "H7 Network Indianapolis Meetup",
      "location": {
        "name": "Westfield",
        "address": "Westfield, Indiana",
        "lat": 40.0428,
        "lng": -86.1275
      },
      "features": {
        "free": false,
        "food": false,
        "appetizers": true,
        "nonAlcoholDrinks": false,
        "alcoholDrinks": false,
        "captainForged": false
      },
      "organizer": "H7 Network Indianapolis Meetup",
      "id": "8686961658012790725"
    },
    {
      "title": "H7 Network, Indianapolis, IN Senior",
      "description": "H7 Indianapolis IN Business Networking\n## Traditions at Solana\n\n*7721 Battery Pointe Way, Indianapolis, IN 46240*\n\n[Add to Calendar](https://www.addevent.com/event/Ph26135585)\n\n**H7 Indianapolis Senior** is our weekly networking meeting open to B2C professionals. Our focus is serving the 55+ community by building a network of professionals that serve this growing audience. Experience the distinct, structural, difference from other networking groups, associations, and chambers.\nOur community of m",
      "url": "https://www.meetup.com/h7-network-indianapolis/events/313850855/",
      "date": "2026-04-08T09:00:00",
      "source": "H7 Network Indianapolis Meetup",
      "location": {
        "name": "Indianapolis",
        "address": "Indianapolis, Indiana",
        "lat": 39.7684,
        "lng": -86.1581
      },
      "features": {
        "free": false,
        "food": false,
        "appetizers": true,
        "nonAlcoholDrinks": false,
        "alcoholDrinks": false,
        "captainForged": false
      },
      "organizer": "H7 Network Indianapolis Meetup",
      "id": "5960683155605143999"
    },
    {
      "title": "H7 Network, Fishers, IN",
      "description": "H7 Indianapolis IN Business Networking\n**Looking for Fishers, IN? Join us every Wednesday at 12:00PM EDT.**\n\n[Add to Calendar](https://www.addevent.com/event/et26135730)\n\n**H7 Fishers** is our weekly networking meeting open to local B2B and B2C professionals. Experience the distinct, structural, difference from other networking groups, associations, and chambers.\nOur community of meetings are led by Champion Leadership.\n\n***All meetings welcome visitors, we'd love to show you what we're all abou",
      "url": "https://www.meetup.com/h7-network-indianapolis/events/313853746/",
      "date": "2026-04-08T12:00:00",
      "source": "H7 Network Indianapolis Meetup",
      "location": {
        "name": "Fishers",
        "address": "Fishers, Indiana",
        "lat": 39.9567,
        "lng": -86.0139
      },
      "features": {
        "free": false,
        "food": false,
        "appetizers": true,
        "nonAlcoholDrinks": false,
        "alcoholDrinks": false,
        "captainForged": false
      },
      "organizer": "H7 Network Indianapolis Meetup",
      "id": "3110259379069055477"
    },
    {
      "title": "H7 Network, Noblesville, IN",
      "description": "H7 Indianapolis IN Business Networking\n**Perkins**\n*250 Noble Creek Dr., Noblesville, IN 46060, USA*\n\n[Add to Calendar](https://www.addevent.com/event/Em26135662)\n\n**H7 Noblesville** is our weekly networking meeting open to local B2B and B2C professionals. Experience the distinct, structural, difference from other networking groups, associations, and chambers. Our community of meetings are led by Champion Leadership.\n\n***All meetings welcome visitors, we'd love to show you what we're all about!*",
      "url": "https://www.meetup.com/h7-network-indianapolis/events/313866817/",
      "date": "2026-04-09T08:00:00",
      "source": "H7 Network Indianapolis Meetup",
      "location": {
        "name": "Noblesville",
        "address": "Noblesville, Indiana",
        "lat": 40.0456,
        "lng": -86.0086
      },
      "features": {
        "free": false,
        "food": false,
        "appetizers": true,
        "nonAlcoholDrinks": false,
        "alcoholDrinks": false,
        "captainForged": false
      },
      "organizer": "H7 Network Indianapolis Meetup",
      "id": "2429010088737943706"
    },
    {
      "title": "H7 Network, Carmel, IN",
      "description": "H7 Indianapolis IN Business Networking\n**Wolfies Grill - Carmel**\n*1162 Keystone Way S, Carmel, IN 46032, USA*\n\nH7 Carmel is our weekly networking meeting open to local B2B and B2C professionals. Experience the distinct, structural, difference from other networking groups, associations, and chambers. Our community of meetings are led by Champion Leadership.\n\n***All meetings welcome visitors, we'd love to show you what we're all about!***\n\n\\*\\*\\*Meeting Contact: \\*\\*\\*\n\n**Seth Wilson** *at* ***31",
      "url": "https://www.meetup.com/h7-network-indianapolis/events/313928213/",
      "date": "2026-04-13T12:00:00",
      "source": "H7 Network Indianapolis Meetup",
      "location": {
        "name": "Carmel",
        "address": "Carmel, Indiana",
        "lat": 39.9784,
        "lng": -86.118
      },
      "features": {
        "free": false,
        "food": false,
        "appetizers": true,
        "nonAlcoholDrinks": false,
        "alcoholDrinks": false,
        "captainForged": false
      },
      "organizer": "H7 Network Indianapolis Meetup",
      "id": "8088331131142556729"
    },
    {
      "title": "H7 Network, Westfield, IN",
      "description": "H7 Indianapolis IN Business Networking\n**Lincoln Square Pancake House**\n*3186 IN-32, Westfield, IN 46074, USA*\n\nH7 Westfield is our weekly networking meeting open to local B2B and B2C professionals. Experience the distinct, structural, difference from other networking groups, associations, and chambers. Our community of meetings are led by Champion Leadership.\n***All meetings welcome visitors, we'd love to show you what we're all about!***\n\n***Meeting Contact*:**\n\n**Andy Corman,** *andy@actrashh",
      "url": "https://www.meetup.com/h7-network-indianapolis/events/313941675/",
      "date": "2026-04-14T08:30:00",
      "source": "H7 Network Indianapolis Meetup",
      "location": {
        "name": "Westfield",
        "address": "Westfield, Indiana",
        "lat": 40.0428,
        "lng": -86.1275
      },
      "features": {
        "free": false,
        "food": false,
        "appetizers": true,
        "nonAlcoholDrinks": false,
        "alcoholDrinks": false,
        "captainForged": false
      },
      "organizer": "H7 Network Indianapolis Meetup",
      "id": "8519427178967128691"
    },
    {
      "title": "H7 Network, Indianapolis, IN Senior",
      "description": "H7 Indianapolis IN Business Networking\n## Traditions at Solana\n\n*7721 Battery Pointe Way, Indianapolis, IN 46240*\n\n[Add to Calendar](https://www.addevent.com/event/Ph26135585)\n\n**H7 Indianapolis Senior** is our weekly networking meeting open to B2C professionals. Our focus is serving the 55+ community by building a network of professionals that serve this growing audience. Experience the distinct, structural, difference from other networking groups, associations, and chambers.\nOur community of m",
      "url": "https://www.meetup.com/h7-network-indianapolis/events/313959802/",
      "date": "2026-04-15T09:00:00",
      "source": "H7 Network Indianapolis Meetup",
      "location": {
        "name": "Indianapolis",
        "address": "Indianapolis, Indiana",
        "lat": 39.7684,
        "lng": -86.1581
      },
      "features": {
        "free": false,
        "food": false,
        "appetizers": true,
        "nonAlcoholDrinks": false,
        "alcoholDrinks": false,
        "captainForged": false
      },
      "organizer": "H7 Network Indianapolis Meetup",
      "id": "6432212015439854887"
    },
    {
      "title": "H7 Network, Fishers, IN",
      "description": "H7 Indianapolis IN Business Networking\n**Looking for Fishers, IN? Join us every Wednesday at 12:00PM EDT.**\n\n[Add to Calendar](https://www.addevent.com/event/et26135730)\n\n**H7 Fishers** is our weekly networking meeting open to local B2B and B2C professionals. Experience the distinct, structural, difference from other networking groups, associations, and chambers.\nOur community of meetings are led by Champion Leadership.\n\n***All meetings welcome visitors, we'd love to show you what we're all abou",
      "url": "https://www.meetup.com/h7-network-indianapolis/events/313962650/",
      "date": "2026-04-15T12:00:00",
      "source": "H7 Network Indianapolis Meetup",
      "location": {
        "name": "Fishers",
        "address": "Fishers, Indiana",
        "lat": 39.9567,
        "lng": -86.0139
      },
      "features": {
        "free": false,
        "food": false,
        "appetizers": true,
        "nonAlcoholDrinks": false,
        "alcoholDrinks": false,
        "captainForged": false
      },
      "organizer": "H7 Network Indianapolis Meetup",
      "id": "389843759799293074"
    },
    {
      "title": "Capital & Coffee: IU Ventures Summit Edition",
      "description": "Join Venture Club of Indiana for coffee before the IU Ventures Summit begins in Bloomington, Indiana! Location will be updated soon and will be close to the IU Ventures Summit.",
      "url": "https://www.ventureclub.org/events-2-1/capital-coffee-iu-ventures-summit-edition",
      "date": "2026-05-21T00:00:00",
      "source": "Venture Club of Indiana",
      "location": {
        "name": "Indianapolis",
        "address": "Indianapolis, IN",
        "lat": 39.7684,
        "lng": -86.1581
      },
      "features": {
        "free": false,
        "food": false,
        "appetizers": false,
        "nonAlcoholDrinks": true,
        "alcoholDrinks": false,
        "captainForged": false
      },
      "organizer": "Venture Club of Indiana",
      "id": "8807617094014785858"
    },
    {
      "title": "Innovation Showcase: Save the Date!",
      "description": "Join the Venture Club of Indiana for its annual Innovation Showcase! Save the date for one of the biggest events in Indiana!",
      "url": "https://www.ventureclub.org/events-2-1/innovation-showcase-save-the-date",
      "date": "2026-06-18T00:00:00",
      "source": "Venture Club of Indiana",
      "location": {
        "name": "Indianapolis",
        "address": "Indianapolis, IN",
        "lat": 39.7684,
        "lng": -86.1581
      },
      "features": {
        "free": false,
        "food": false,
        "appetizers": false,
        "nonAlcoholDrinks": false,
        "alcoholDrinks": false,
        "captainForged": false
      },
      "organizer": "Venture Club of Indiana",
      "id": "191239205441522405"
    },
    {
      "title": "Remote Worker Luncheon",
      "description": "Remote Worker Luncheon",
      "url": "https://mbx.studio/events/remote-worker-luncheon",
      "date": "2026-04-10T00:00:00",
      "source": "MatchBOX Coworking Studio",
      "location": {
        "name": "MatchBOX Coworking Studio",
        "address": "Lafayette, IN",
        "lat": 40.4191229,
        "lng": -86.8919011
      },
      "features": {
        "free": false,
        "food": true,
        "appetizers": false,
        "nonAlcoholDrinks": false,
        "alcoholDrinks": false,
        "captainForged": false
      },
      "organizer": "MatchBOX Coworking Studio",
      "id": "8072801600706397659"
    },
    {
      "title": "Non-Members",
      "description": "This workshop introduces participants to the art of creating wearable patches. In just two hours, you\u2019ll learn how to prepare a preset design to craft an embroidered patch using the Brother SE1900.",
      "url": "?category=Non-Members",
      "date": "2026-04-08T00:00:00",
      "source": "Madjax Maker Force",
      "location": {
        "name": "Madjax Maker Force",
        "address": "515 E Main St, Muncie, IN 47305",
        "lat": 40.1935076,
        "lng": -85.381463
      },
      "features": {
        "free": false,
        "food": false,
        "appetizers": false,
        "nonAlcoholDrinks": false,
        "alcoholDrinks": false,
        "captainForged": false
      },
      "organizer": "Madjax Maker Force",
      "id": "2205053211241326207"
    },
    {
      "title": "Fishers Code & Coffee",
      "description": "Fishers Code and Coffee\nMeeting time: 7a to 8:30a\nLocation: The Well, Fishers, [8890 E 116th St, Fishers, IN 46038](https://www.bing.com/ck/a?!&&p=4404c76747fcd866JmltdHM9MTcxMDYzMzYwMCZpZ3VpZD0yY2JkZTEzNy0wODZmLTZkODktMWYwZC1mM2IwMDkxMTZjZTMmaW5zaWQ9NTY1Ng&ptn=3&ver=2&hsh=3&fclid=2cbde137-086f-6d89-1f0d-f3b009116ce3&u=a1L21hcHM_Jm1lcGk9MTAxfn5Vbmtub3dufkFkZHJlc3NfTGluayZ0eT0xOCZxPVRoZSUyMFdlbGwlMjBDb2ZmZWVob3VzZSUyMEZpc2hlcnMmc3M9eXBpZC5ZTjg3M3g5NzAwOTg2NjUyNTg3NzE4MzAzJnBwb2lzPTM5Ljk1NzE4MDAyM",
      "url": "https://www.meetup.com/fishers-code-coffee/events/313832354/",
      "date": "2026-04-07T07:00:00",
      "source": "Fishers Code and Coffee Meetup",
      "location": {
        "name": "Fishers",
        "address": "Fishers, Indiana",
        "lat": 39.9567,
        "lng": -86.0139
      },
      "features": {
        "free": false,
        "food": false,
        "appetizers": false,
        "nonAlcoholDrinks": true,
        "alcoholDrinks": false,
        "captainForged": false
      },
      "organizer": "Fishers Code and Coffee Meetup",
      "id": "2552113055430267076"
    },
    {
      "title": "Fishers Code & Coffee",
      "description": "Fishers Code and Coffee\nMeeting time: 7a to 8:30a\nLocation: The Well, Fishers, [8890 E 116th St, Fishers, IN 46038](https://www.bing.com/ck/a?!&&p=4404c76747fcd866JmltdHM9MTcxMDYzMzYwMCZpZ3VpZD0yY2JkZTEzNy0wODZmLTZkODktMWYwZC1mM2IwMDkxMTZjZTMmaW5zaWQ9NTY1Ng&ptn=3&ver=2&hsh=3&fclid=2cbde137-086f-6d89-1f0d-f3b009116ce3&u=a1L21hcHM_Jm1lcGk9MTAxfn5Vbmtub3dufkFkZHJlc3NfTGluayZ0eT0xOCZxPVRoZSUyMFdlbGwlMjBDb2ZmZWVob3VzZSUyMEZpc2hlcnMmc3M9eXBpZC5ZTjg3M3g5NzAwOTg2NjUyNTg3NzE4MzAzJnBwb2lzPTM5Ljk1NzE4MDAyM",
      "url": "https://www.meetup.com/fishers-code-coffee/events/313940882/",
      "date": "2026-04-14T07:00:00",
      "source": "Fishers Code and Coffee Meetup",
      "location": {
        "name": "Fishers",
        "address": "Fishers, Indiana",
        "lat": 39.9567,
        "lng": -86.0139
      },
      "features": {
        "free": false,
        "food": false,
        "appetizers": false,
        "nonAlcoholDrinks": true,
        "alcoholDrinks": false,
        "captainForged": false
      },
      "organizer": "Fishers Code and Coffee Meetup",
      "id": "2112722447796778501"
    },
    {
      "title": "Fishers Code & Coffee",
      "description": "Fishers Code and Coffee\nMeeting time: 7a to 8:30a\nLocation: The Well, Fishers, [8890 E 116th St, Fishers, IN 46038](https://www.bing.com/ck/a?!&&p=4404c76747fcd866JmltdHM9MTcxMDYzMzYwMCZpZ3VpZD0yY2JkZTEzNy0wODZmLTZkODktMWYwZC1mM2IwMDkxMTZjZTMmaW5zaWQ9NTY1Ng&ptn=3&ver=2&hsh=3&fclid=2cbde137-086f-6d89-1f0d-f3b009116ce3&u=a1L21hcHM_Jm1lcGk9MTAxfn5Vbmtub3dufkFkZHJlc3NfTGluayZ0eT0xOCZxPVRoZSUyMFdlbGwlMjBDb2ZmZWVob3VzZSUyMEZpc2hlcnMmc3M9eXBpZC5ZTjg3M3g5NzAwOTg2NjUyNTg3NzE4MzAzJnBwb2lzPTM5Ljk1NzE4MDAyM",
      "url": "https://www.meetup.com/fishers-code-coffee/events/314069817/",
      "date": "2026-04-21T07:00:00",
      "source": "Fishers Code and Coffee Meetup",
      "location": {
        "name": "Fishers",
        "address": "Fishers, Indiana",
        "lat": 39.9567,
        "lng": -86.0139
      },
      "features": {
        "free": false,
        "food": false,
        "appetizers": false,
        "nonAlcoholDrinks": true,
        "alcoholDrinks": false,
        "captainForged": false
      },
      "organizer": "Fishers Code and Coffee Meetup",
      "id": "6370846111117881283"
    },
    {
      "title": "Fishers Code & Coffee",
      "description": "Fishers Code and Coffee\nMeeting time: 7a to 8:30a\nLocation: The Well, Fishers, [8890 E 116th St, Fishers, IN 46038](https://www.bing.com/ck/a?!&&p=4404c76747fcd866JmltdHM9MTcxMDYzMzYwMCZpZ3VpZD0yY2JkZTEzNy0wODZmLTZkODktMWYwZC1mM2IwMDkxMTZjZTMmaW5zaWQ9NTY1Ng&ptn=3&ver=2&hsh=3&fclid=2cbde137-086f-6d89-1f0d-f3b009116ce3&u=a1L21hcHM_Jm1lcGk9MTAxfn5Vbmtub3dufkFkZHJlc3NfTGluayZ0eT0xOCZxPVRoZSUyMFdlbGwlMjBDb2ZmZWVob3VzZSUyMEZpc2hlcnMmc3M9eXBpZC5ZTjg3M3g5NzAwOTg2NjUyNTg3NzE4MzAzJnBwb2lzPTM5Ljk1NzE4MDAyM",
      "url": "https://www.meetup.com/fishers-code-coffee/events/bsqvktyjcgblc/",
      "date": "2026-04-28T07:00:00",
      "source": "Fishers Code and Coffee Meetup",
      "location": {
        "name": "Fishers",
        "address": "Fishers, Indiana",
        "lat": 39.9567,
        "lng": -86.0139
      },
      "features": {
        "free": false,
        "food": false,
        "appetizers": false,
        "nonAlcoholDrinks": true,
        "alcoholDrinks": false,
        "captainForged": false
      },
      "organizer": "Fishers Code and Coffee Meetup",
      "id": "6328622419625934342"
    },
    {
      "title": "Fishers Code & Coffee",
      "description": "Fishers Code and Coffee\nMeeting time: 7a to 8:30a\nLocation: The Well, Fishers, [8890 E 116th St, Fishers, IN 46038](https://www.bing.com/ck/a?!&&p=4404c76747fcd866JmltdHM9MTcxMDYzMzYwMCZpZ3VpZD0yY2JkZTEzNy0wODZmLTZkODktMWYwZC1mM2IwMDkxMTZjZTMmaW5zaWQ9NTY1Ng&ptn=3&ver=2&hsh=3&fclid=2cbde137-086f-6d89-1f0d-f3b009116ce3&u=a1L21hcHM_Jm1lcGk9MTAxfn5Vbmtub3dufkFkZHJlc3NfTGluayZ0eT0xOCZxPVRoZSUyMFdlbGwlMjBDb2ZmZWVob3VzZSUyMEZpc2hlcnMmc3M9eXBpZC5ZTjg3M3g5NzAwOTg2NjUyNTg3NzE4MzAzJnBwb2lzPTM5Ljk1NzE4MDAyM",
      "url": "https://www.meetup.com/fishers-code-coffee/events/bsqvktyjchbhb/",
      "date": "2026-05-05T07:00:00",
      "source": "Fishers Code and Coffee Meetup",
      "location": {
        "name": "Fishers",
        "address": "Fishers, Indiana",
        "lat": 39.9567,
        "lng": -86.0139
      },
      "features": {
        "free": false,
        "food": false,
        "appetizers": false,
        "nonAlcoholDrinks": true,
        "alcoholDrinks": false,
        "captainForged": false
      },
      "organizer": "Fishers Code and Coffee Meetup",
      "id": "4773870382805768793"
    },
    {
      "title": "Fishers Code & Coffee",
      "description": "Fishers Code and Coffee\nMeeting time: 7a to 8:30a\nLocation: The Well, Fishers, [8890 E 116th St, Fishers, IN 46038](https://www.bing.com/ck/a?!&&p=4404c76747fcd866JmltdHM9MTcxMDYzMzYwMCZpZ3VpZD0yY2JkZTEzNy0wODZmLTZkODktMWYwZC1mM2IwMDkxMTZjZTMmaW5zaWQ9NTY1Ng&ptn=3&ver=2&hsh=3&fclid=2cbde137-086f-6d89-1f0d-f3b009116ce3&u=a1L21hcHM_Jm1lcGk9MTAxfn5Vbmtub3dufkFkZHJlc3NfTGluayZ0eT0xOCZxPVRoZSUyMFdlbGwlMjBDb2ZmZWVob3VzZSUyMEZpc2hlcnMmc3M9eXBpZC5ZTjg3M3g5NzAwOTg2NjUyNTg3NzE4MzAzJnBwb2lzPTM5Ljk1NzE4MDAyM",
      "url": "https://www.meetup.com/fishers-code-coffee/events/bsqvktyjchbqb/",
      "date": "2026-05-12T07:00:00",
      "source": "Fishers Code and Coffee Meetup",
      "location": {
        "name": "Fishers",
        "address": "Fishers, Indiana",
        "lat": 39.9567,
        "lng": -86.0139
      },
      "features": {
        "free": false,
        "food": false,
        "appetizers": false,
        "nonAlcoholDrinks": true,
        "alcoholDrinks": false,
        "captainForged": false
      },
      "organizer": "Fishers Code and Coffee Meetup",
      "id": "2295813503384300160"
    },
    {
      "title": "Fishers Code & Coffee",
      "description": "Fishers Code and Coffee\nMeeting time: 7a to 8:30a\nLocation: The Well, Fishers, [8890 E 116th St, Fishers, IN 46038](https://www.bing.com/ck/a?!&&p=4404c76747fcd866JmltdHM9MTcxMDYzMzYwMCZpZ3VpZD0yY2JkZTEzNy0wODZmLTZkODktMWYwZC1mM2IwMDkxMTZjZTMmaW5zaWQ9NTY1Ng&ptn=3&ver=2&hsh=3&fclid=2cbde137-086f-6d89-1f0d-f3b009116ce3&u=a1L21hcHM_Jm1lcGk9MTAxfn5Vbmtub3dufkFkZHJlc3NfTGluayZ0eT0xOCZxPVRoZSUyMFdlbGwlMjBDb2ZmZWVob3VzZSUyMEZpc2hlcnMmc3M9eXBpZC5ZTjg3M3g5NzAwOTg2NjUyNTg3NzE4MzAzJnBwb2lzPTM5Ljk1NzE4MDAyM",
      "url": "https://www.meetup.com/fishers-code-coffee/events/bsqvktyjchbzb/",
      "date": "2026-05-19T07:00:00",
      "source": "Fishers Code and Coffee Meetup",
      "location": {
        "name": "Fishers",
        "address": "Fishers, Indiana",
        "lat": 39.9567,
        "lng": -86.0139
      },
      "features": {
        "free": false,
        "food": false,
        "appetizers": false,
        "nonAlcoholDrinks": true,
        "alcoholDrinks": false,
        "captainForged": false
      },
      "organizer": "Fishers Code and Coffee Meetup",
      "id": "1470856163701997798"
    },
    {
      "title": "Fishers Code & Coffee",
      "description": "Fishers Code and Coffee\nMeeting time: 7a to 8:30a\nLocation: The Well, Fishers, [8890 E 116th St, Fishers, IN 46038](https://www.bing.com/ck/a?!&&p=4404c76747fcd866JmltdHM9MTcxMDYzMzYwMCZpZ3VpZD0yY2JkZTEzNy0wODZmLTZkODktMWYwZC1mM2IwMDkxMTZjZTMmaW5zaWQ9NTY1Ng&ptn=3&ver=2&hsh=3&fclid=2cbde137-086f-6d89-1f0d-f3b009116ce3&u=a1L21hcHM_Jm1lcGk9MTAxfn5Vbmtub3dufkFkZHJlc3NfTGluayZ0eT0xOCZxPVRoZSUyMFdlbGwlMjBDb2ZmZWVob3VzZSUyMEZpc2hlcnMmc3M9eXBpZC5ZTjg3M3g5NzAwOTg2NjUyNTg3NzE4MzAzJnBwb2lzPTM5Ljk1NzE4MDAyM",
      "url": "https://www.meetup.com/fishers-code-coffee/events/bsqvktyjchbjc/",
      "date": "2026-05-26T07:00:00",
      "source": "Fishers Code and Coffee Meetup",
      "location": {
        "name": "Fishers",
        "address": "Fishers, Indiana",
        "lat": 39.9567,
        "lng": -86.0139
      },
      "features": {
        "free": false,
        "food": false,
        "appetizers": false,
        "nonAlcoholDrinks": true,
        "alcoholDrinks": false,
        "captainForged": false
      },
      "organizer": "Fishers Code and Coffee Meetup",
      "id": "8790247848379019111"
    },
    {
      "title": "Fishers Code & Coffee",
      "description": "Fishers Code and Coffee\nMeeting time: 7a to 8:30a\nLocation: The Well, Fishers, [8890 E 116th St, Fishers, IN 46038](https://www.bing.com/ck/a?!&&p=4404c76747fcd866JmltdHM9MTcxMDYzMzYwMCZpZ3VpZD0yY2JkZTEzNy0wODZmLTZkODktMWYwZC1mM2IwMDkxMTZjZTMmaW5zaWQ9NTY1Ng&ptn=3&ver=2&hsh=3&fclid=2cbde137-086f-6d89-1f0d-f3b009116ce3&u=a1L21hcHM_Jm1lcGk9MTAxfn5Vbmtub3dufkFkZHJlc3NfTGluayZ0eT0xOCZxPVRoZSUyMFdlbGwlMjBDb2ZmZWVob3VzZSUyMEZpc2hlcnMmc3M9eXBpZC5ZTjg3M3g5NzAwOTg2NjUyNTg3NzE4MzAzJnBwb2lzPTM5Ljk1NzE4MDAyM",
      "url": "https://www.meetup.com/fishers-code-coffee/events/bsqvktyjcjbdb/",
      "date": "2026-06-02T07:00:00",
      "source": "Fishers Code and Coffee Meetup",
      "location": {
        "name": "Fishers",
        "address": "Fishers, Indiana",
        "lat": 39.9567,
        "lng": -86.0139
      },
      "features": {
        "free": false,
        "food": false,
        "appetizers": false,
        "nonAlcoholDrinks": true,
        "alcoholDrinks": false,
        "captainForged": false
      },
      "organizer": "Fishers Code and Coffee Meetup",
      "id": "4813818782768984837"
    },
    {
      "title": "Fishers Code & Coffee",
      "description": "Fishers Code and Coffee\nMeeting time: 7a to 8:30a\nLocation: The Well, Fishers, [8890 E 116th St, Fishers, IN 46038](https://www.bing.com/ck/a?!&&p=4404c76747fcd866JmltdHM9MTcxMDYzMzYwMCZpZ3VpZD0yY2JkZTEzNy0wODZmLTZkODktMWYwZC1mM2IwMDkxMTZjZTMmaW5zaWQ9NTY1Ng&ptn=3&ver=2&hsh=3&fclid=2cbde137-086f-6d89-1f0d-f3b009116ce3&u=a1L21hcHM_Jm1lcGk9MTAxfn5Vbmtub3dufkFkZHJlc3NfTGluayZ0eT0xOCZxPVRoZSUyMFdlbGwlMjBDb2ZmZWVob3VzZSUyMEZpc2hlcnMmc3M9eXBpZC5ZTjg3M3g5NzAwOTg2NjUyNTg3NzE4MzAzJnBwb2lzPTM5Ljk1NzE4MDAyM",
      "url": "https://www.meetup.com/fishers-code-coffee/events/bsqvktyjcjbmb/",
      "date": "2026-06-09T07:00:00",
      "source": "Fishers Code and Coffee Meetup",
      "location": {
        "name": "Fishers",
        "address": "Fishers, Indiana",
        "lat": 39.9567,
        "lng": -86.0139
      },
      "features": {
        "free": false,
        "food": false,
        "appetizers": false,
        "nonAlcoholDrinks": true,
        "alcoholDrinks": false,
        "captainForged": false
      },
      "organizer": "Fishers Code and Coffee Meetup",
      "id": "737952776200795173"
    },
    {
      "title": "Indy.rb - The Indianapolis Ruby Brigade Monthly Meetup",
      "description": "Indyrb - Indianapolis Ruby Brigade\nJoin us to talk about Ruby, work projects, hack on something, or just get a drink or bite & enjoy the company.\n\nWe are mixing it up again and meeting this month at The Ale Emporium Castleton location\n8617 Allisonville Rd\nIndianapolis, 46250\nhttps://www.ale-emporium.com/Locations/indianapolis\nhttps://www.google.com/maps/place/Ale+Emporium/@39.9133356,-86.0747701,16z/data=!3m1!4b1!4m6!3m5!1s0x886b4d4af5b13331:0xc61bc6f9f216e716!8m2!3d39.9133315!4d-86.0721952!16s%",
      "url": "https://www.meetup.com/indyrb/events/313859567/",
      "date": "2026-04-08T19:00:00",
      "source": "Indy.rb Ruby Brigade Meetup",
      "location": {
        "name": "Indianapolis",
        "address": "Indianapolis, Indiana",
        "lat": 39.7684,
        "lng": -86.1581
      },
      "features": {
        "free": false,
        "food": false,
        "appetizers": true,
        "nonAlcoholDrinks": false,
        "alcoholDrinks": false,
        "captainForged": false
      },
      "organizer": "Indy.rb Ruby Brigade Meetup",
      "id": "6108470678506705322"
    },
    {
      "title": "Indy.rb - The Indianapolis Ruby Brigade Monthly Meetup",
      "description": "Indyrb - Indianapolis Ruby Brigade\nJoin us to talk about Ruby, work projects, hack on something, or just get a drink or bite & enjoy the company.\n\nWe are mixing it up again and meeting this month at The Ale Emporium Castleton location\n8617 Allisonville Rd\nIndianapolis, 46250\nhttps://www.ale-emporium.com/Locations/indianapolis\nhttps://www.google.com/maps/place/Ale+Emporium/@39.9133356,-86.0747701,16z/data=!3m1!4b1!4m6!3m5!1s0x886b4d4af5b13331:0xc61bc6f9f216e716!8m2!3d39.9133315!4d-86.0721952!16s%",
      "url": "https://www.meetup.com/indyrb/events/bprjttyjchbrb/",
      "date": "2026-05-13T19:00:00",
      "source": "Indy.rb Ruby Brigade Meetup",
      "location": {
        "name": "Indianapolis",
        "address": "Indianapolis, Indiana",
        "lat": 39.7684,
        "lng": -86.1581
      },
      "features": {
        "free": false,
        "food": false,
        "appetizers": true,
        "nonAlcoholDrinks": false,
        "alcoholDrinks": false,
        "captainForged": false
      },
      "organizer": "Indy.rb Ruby Brigade Meetup",
      "id": "8362088668116997567"
    },
    {
      "title": "Indy.rb - The Indianapolis Ruby Brigade Monthly Meetup",
      "description": "Indyrb - Indianapolis Ruby Brigade\nJoin us to talk about Ruby, work projects, hack on something, or just get a drink or bite & enjoy the company.\n\nWe are mixing it up again and meeting this month at The Ale Emporium Castleton location\n8617 Allisonville Rd\nIndianapolis, 46250\nhttps://www.ale-emporium.com/Locations/indianapolis\nhttps://www.google.com/maps/place/Ale+Emporium/@39.9133356,-86.0747701,16z/data=!3m1!4b1!4m6!3m5!1s0x886b4d4af5b13331:0xc61bc6f9f216e716!8m2!3d39.9133315!4d-86.0721952!16s%",
      "url": "https://www.meetup.com/indyrb/events/bprjttyjcjbnb/",
      "date": "2026-06-10T19:00:00",
      "source": "Indy.rb Ruby Brigade Meetup",
      "location": {
        "name": "Indianapolis",
        "address": "Indianapolis, Indiana",
        "lat": 39.7684,
        "lng": -86.1581
      },
      "features": {
        "free": false,
        "food": false,
        "appetizers": true,
        "nonAlcoholDrinks": false,
        "alcoholDrinks": false,
        "captainForged": false
      },
      "organizer": "Indy.rb Ruby Brigade Meetup",
      "id": "29200669760744274"
    },
    {
      "title": "Indy.rb - The Indianapolis Ruby Brigade Monthly Meetup",
      "description": "Indyrb - Indianapolis Ruby Brigade\nJoin us to talk about Ruby, work projects, hack on something, or just get a drink or bite & enjoy the company.\n\nWe are mixing it up again and meeting this month at The Ale Emporium Castleton location\n8617 Allisonville Rd\nIndianapolis, 46250\nhttps://www.ale-emporium.com/Locations/indianapolis\nhttps://www.google.com/maps/place/Ale+Emporium/@39.9133356,-86.0747701,16z/data=!3m1!4b1!4m6!3m5!1s0x886b4d4af5b13331:0xc61bc6f9f216e716!8m2!3d39.9133315!4d-86.0721952!16s%",
      "url": "https://www.meetup.com/indyrb/events/bprjttyjckblb/",
      "date": "2026-07-08T19:00:00",
      "source": "Indy.rb Ruby Brigade Meetup",
      "location": {
        "name": "Indianapolis",
        "address": "Indianapolis, Indiana",
        "lat": 39.7684,
        "lng": -86.1581
      },
      "features": {
        "free": false,
        "food": false,
        "appetizers": true,
        "nonAlcoholDrinks": false,
        "alcoholDrinks": false,
        "captainForged": false
      },
      "organizer": "Indy.rb Ruby Brigade Meetup",
      "id": "4518104152318046924"
    },
    {
      "title": "Indy.rb - The Indianapolis Ruby Brigade Monthly Meetup",
      "description": "Indyrb - Indianapolis Ruby Brigade\nJoin us to talk about Ruby, work projects, hack on something, or just get a drink or bite & enjoy the company.\n\nWe are mixing it up again and meeting this month at The Ale Emporium Castleton location\n8617 Allisonville Rd\nIndianapolis, 46250\nhttps://www.ale-emporium.com/Locations/indianapolis\nhttps://www.google.com/maps/place/Ale+Emporium/@39.9133356,-86.0747701,16z/data=!3m1!4b1!4m6!3m5!1s0x886b4d4af5b13331:0xc61bc6f9f216e716!8m2!3d39.9133315!4d-86.0721952!16s%",
      "url": "https://www.meetup.com/indyrb/events/bprjttyjclbqb/",
      "date": "2026-08-12T19:00:00",
      "source": "Indy.rb Ruby Brigade Meetup",
      "location": {
        "name": "Indianapolis",
        "address": "Indianapolis, Indiana",
        "lat": 39.7684,
        "lng": -86.1581
      },
      "features": {
        "free": false,
        "food": false,
        "appetizers": true,
        "nonAlcoholDrinks": false,
        "alcoholDrinks": false,
        "captainForged": false
      },
      "organizer": "Indy.rb Ruby Brigade Meetup",
      "id": "2545180045730004330"
    },
    {
      "title": "Indy.rb - The Indianapolis Ruby Brigade Monthly Meetup",
      "description": "Indyrb - Indianapolis Ruby Brigade\nJoin us to talk about Ruby, work projects, hack on something, or just get a drink or bite & enjoy the company.\n\nWe are mixing it up again and meeting this month at The Ale Emporium Castleton location\n8617 Allisonville Rd\nIndianapolis, 46250\nhttps://www.ale-emporium.com/Locations/indianapolis\nhttps://www.google.com/maps/place/Ale+Emporium/@39.9133356,-86.0747701,16z/data=!3m1!4b1!4m6!3m5!1s0x886b4d4af5b13331:0xc61bc6f9f216e716!8m2!3d39.9133315!4d-86.0721952!16s%",
      "url": "https://www.meetup.com/indyrb/events/bprjttyjcmbmb/",
      "date": "2026-09-09T19:00:00",
      "source": "Indy.rb Ruby Brigade Meetup",
      "location": {
        "name": "Indianapolis",
        "address": "Indianapolis, Indiana",
        "lat": 39.7684,
        "lng": -86.1581
      },
      "features": {
        "free": false,
        "food": false,
        "appetizers": true,
        "nonAlcoholDrinks": false,
        "alcoholDrinks": false,
        "captainForged": false
      },
      "organizer": "Indy.rb Ruby Brigade Meetup",
      "id": "190257678200856703"
    },
    {
      "title": "Indy.rb - The Indianapolis Ruby Brigade Monthly Meetup",
      "description": "Indyrb - Indianapolis Ruby Brigade\nJoin us to talk about Ruby, work projects, hack on something, or just get a drink or bite & enjoy the company.\n\nWe are mixing it up again and meeting this month at The Ale Emporium Castleton location\n8617 Allisonville Rd\nIndianapolis, 46250\nhttps://www.ale-emporium.com/Locations/indianapolis\nhttps://www.google.com/maps/place/Ale+Emporium/@39.9133356,-86.0747701,16z/data=!3m1!4b1!4m6!3m5!1s0x886b4d4af5b13331:0xc61bc6f9f216e716!8m2!3d39.9133315!4d-86.0721952!16s%",
      "url": "https://www.meetup.com/indyrb/events/bprjttyjcnbsb/",
      "date": "2026-10-14T19:00:00",
      "source": "Indy.rb Ruby Brigade Meetup",
      "location": {
        "name": "Indianapolis",
        "address": "Indianapolis, Indiana",
        "lat": 39.7684,
        "lng": -86.1581
      },
      "features": {
        "free": false,
        "food": false,
        "appetizers": true,
        "nonAlcoholDrinks": false,
        "alcoholDrinks": false,
        "captainForged": false
      },
      "organizer": "Indy.rb Ruby Brigade Meetup",
      "id": "655453527716151869"
    },
    {
      "title": "Indy.rb - The Indianapolis Ruby Brigade Monthly Meetup",
      "description": "Indyrb - Indianapolis Ruby Brigade\nJoin us to talk about Ruby, work projects, hack on something, or just get a drink or bite & enjoy the company.\n\nWe are mixing it up again and meeting this month at The Ale Emporium Castleton location\n8617 Allisonville Rd\nIndianapolis, 46250\nhttps://www.ale-emporium.com/Locations/indianapolis\nhttps://www.google.com/maps/place/Ale+Emporium/@39.9133356,-86.0747701,16z/data=!3m1!4b1!4m6!3m5!1s0x886b4d4af5b13331:0xc61bc6f9f216e716!8m2!3d39.9133315!4d-86.0721952!16s%",
      "url": "https://www.meetup.com/indyrb/events/bprjttyjcpbpb/",
      "date": "2026-11-11T19:00:00",
      "source": "Indy.rb Ruby Brigade Meetup",
      "location": {
        "name": "Indianapolis",
        "address": "Indianapolis, Indiana",
        "lat": 39.7684,
        "lng": -86.1581
      },
      "features": {
        "free": false,
        "food": false,
        "appetizers": true,
        "nonAlcoholDrinks": false,
        "alcoholDrinks": false,
        "captainForged": false
      },
      "organizer": "Indy.rb Ruby Brigade Meetup",
      "id": "4225172999457751022"
    },
    {
      "title": "Indy.rb - The Indianapolis Ruby Brigade Monthly Meetup",
      "description": "Indyrb - Indianapolis Ruby Brigade\nJoin us to talk about Ruby, work projects, hack on something, or just get a drink or bite & enjoy the company.\n\nWe are mixing it up again and meeting this month at The Ale Emporium Castleton location\n8617 Allisonville Rd\nIndianapolis, 46250\nhttps://www.ale-emporium.com/Locations/indianapolis\nhttps://www.google.com/maps/place/Ale+Emporium/@39.9133356,-86.0747701,16z/data=!3m1!4b1!4m6!3m5!1s0x886b4d4af5b13331:0xc61bc6f9f216e716!8m2!3d39.9133315!4d-86.0721952!16s%",
      "url": "https://www.meetup.com/indyrb/events/bprjttyjcqbmb/",
      "date": "2026-12-09T19:00:00",
      "source": "Indy.rb Ruby Brigade Meetup",
      "location": {
        "name": "Indianapolis",
        "address": "Indianapolis, Indiana",
        "lat": 39.7684,
        "lng": -86.1581
      },
      "features": {
        "free": false,
        "food": false,
        "appetizers": true,
        "nonAlcoholDrinks": false,
        "alcoholDrinks": false,
        "captainForged": false
      },
      "organizer": "Indy.rb Ruby Brigade Meetup",
      "id": "3996828502774694146"
    },
    {
      "title": "Indy.rb - The Indianapolis Ruby Brigade Monthly Meetup",
      "description": "Indyrb - Indianapolis Ruby Brigade\nJoin us to talk about Ruby, work projects, hack on something, or just get a drink or bite & enjoy the company.\n\nWe are mixing it up again and meeting this month at The Ale Emporium Castleton location\n8617 Allisonville Rd\nIndianapolis, 46250\nhttps://www.ale-emporium.com/Locations/indianapolis\nhttps://www.google.com/maps/place/Ale+Emporium/@39.9133356,-86.0747701,16z/data=!3m1!4b1!4m6!3m5!1s0x886b4d4af5b13331:0xc61bc6f9f216e716!8m2!3d39.9133315!4d-86.0721952!16s%",
      "url": "https://www.meetup.com/indyrb/events/bprjttykccbrb/",
      "date": "2027-01-13T19:00:00",
      "source": "Indy.rb Ruby Brigade Meetup",
      "location": {
        "name": "Indianapolis",
        "address": "Indianapolis, Indiana",
        "lat": 39.7684,
        "lng": -86.1581
      },
      "features": {
        "free": false,
        "food": false,
        "appetizers": true,
        "nonAlcoholDrinks": false,
        "alcoholDrinks": false,
        "captainForged": false
      },
      "organizer": "Indy.rb Ruby Brigade Meetup",
      "id": "3500251799323070152"
    }
  ]
}